nshogi.cpython-310-x86_64-linux-gnu.so
nshogi-0.2.3.data/data/NSHOGI_VERSION
nshogi.libs/libcrypt-52aca757.so.1.1.0
nshogi-0.2.3.dist-info/METADATA
nshogi-0.2.3.dist-info/WHEEL
nshogi-0.2.3.dist-info/top_level.txt
nshogi-0.2.3.dist-info/RECORD
nshogi-0.2.3.dist-info/licenses/LICENSE
nshogi-0.2.3.dist-info/licenses/LICENSE-THIRD-PARTY.md
nshogi-0.2.3.dist-info/sboms/auditwheel.cdx.json
