Metadata-Version: 2.4
Name: nshogi
Version: 0.2.3
Summary: nshogi Python library
Author: nyashiki
License: MIT
License-File: LICENSE
License-File: LICENSE-THIRD-PARTY.md
Dynamic: author
Dynamic: license
Dynamic: license-file
Dynamic: summary
